puffy/__init__.py
puffy/error/__init__.py
puffy/log/__init__.py
puffy/object/__init__.py
puffy-0.4.0.dist-info/LICENSE
puffy-0.4.0.dist-info/METADATA
puffy-0.4.0.dist-info/WHEEL
puffy-0.4.0.dist-info/top_level.txt
puffy-0.4.0.dist-info/RECORD
