Metadata-Version: 2.1
Name: puffy
Version: 0.4.0
Summary: A collection of modules with zero-dependencies to help manage common programming tasks.
Home-page: https://github.com/nicolasdao/pypuffy
Author: Nicolas Dao
Author-email: nicolas.dao@gmail.com
License: BSD-3-Clause
Keywords: util
Classifier: Programming Language :: Python :: 3
Classifier: License :: OSI Approved :: BSD License
Requires-Python: >=3.7
License-File: LICENSE
Provides-Extra: dev
Requires-Dist: black ; extra == 'dev'
Requires-Dist: build ; extra == 'dev'
Requires-Dist: easypipinstall ; extra == 'dev'
Requires-Dist: flake8 ; extra == 'dev'
Requires-Dist: pytest ; extra == 'dev'
Requires-Dist: twine ; extra == 'dev'
